dy/DiscrFinState_DiscrInfinTime_DiscValue.py
dy/__init__.py
dy-0.0.1.dist-info/DESCRIPTION.rst
dy-0.0.1.dist-info/METADATA
dy-0.0.1.dist-info/RECORD
dy-0.0.1.dist-info/WHEEL
dy-0.0.1.dist-info/metadata.json
dy-0.0.1.dist-info/top_level.txt
