Metadata-Version: 2.0
Name: dy
Version: 0.0.1
Summary: Dynamic Optimization / Dynamic Programming
Home-page: https://github.com/MBALearnsToCode/PyDy
Author: MBA Learns to Code
Author-email: MBALearnsToCode@UChicago.edu
License: MIT License
Keywords: dynamic optimization programming
Platform: UNKNOWN
